src/yoklama/__init__.py
src/yoklama/ders.py
src/yoklama/ogrenciler.py
src/yoklama/yariyil.py
src/yoklama/yoklama.py
yoklama_kadirhanpolat-0.0.2.dist-info/METADATA
yoklama_kadirhanpolat-0.0.2.dist-info/WHEEL
yoklama_kadirhanpolat-0.0.2.dist-info/RECORD
